deepstkit/__init__.py
deepstkit/_compat.py
deepstkit/_version.py
deepstkit/adj.py
deepstkit/augment.py
deepstkit/his_feat.py
deepstkit/main.py
deepstkit/model.py
deepstkit/trainer.py
deepstkit/utils_func.py
deepstkit-2.0.3.dist-info/licenses/LICENSE
deepstkit-2.0.3.dist-info/METADATA
deepstkit-2.0.3.dist-info/WHEEL
deepstkit-2.0.3.dist-info/top_level.txt
deepstkit-2.0.3.dist-info/RECORD
