Metadata-Version: 2.4
Name: deepstkit
Version: 2.0.3
Summary: Identification of spatial domains in spatial transcriptomics by deep learning.
Home-page: https://github.com/EsdenRun/DeepST
Author: XU CHANG
Author-email: xuchang0214@163.com
License: MIT
Classifier: Programming Language :: Python :: 3
Classifier: License :: OSI Approved :: MIT License
Classifier: Operating System :: OS Independent
Requires-Python: >=3.9
License-File: LICENSE
Requires-Dist: scanpy==1.10.3
Requires-Dist: igraph==0.11.8
Requires-Dist: leidenalg
Requires-Dist: louvain
Dynamic: author
Dynamic: classifier
Dynamic: description
Dynamic: description-content-type
Dynamic: home-page
Dynamic: license
Dynamic: license-file
Dynamic: requires-dist
Dynamic: requires-python
Dynamic: summary
